ts/__init__.py
ts/arg_parser.py
ts/async_service.py
ts/context.py
ts/launcher.py
ts/llm_launcher.py
ts/model_loader.py
ts/model_server.py
ts/model_service_worker.py
ts/service.py
ts/version.py
ts/version.txt
ts/configs/metrics.yaml
ts/configs/sagemaker_config.properties
ts/frontend/model-server.jar
ts/handler_utils/__init__.py
ts/handler_utils/hf_batch_streamer.py
ts/handler_utils/micro_batching.py
ts/handler_utils/text_utils.py
ts/handler_utils/timer.py
ts/handler_utils/utils.py
ts/handler_utils/distributed/__init__.py
ts/handler_utils/distributed/deepspeed.py
ts/handler_utils/distributed/pt_pippy.py
ts/handler_utils/preprocess/__init__.py
ts/handler_utils/preprocess/dali.py
ts/handler_utils/preprocess/built-in/__init__.py
ts/handler_utils/preprocess/built-in/dali_pipeline_generation.py
ts/metrics/__init__.py
ts/metrics/caching_metric.py
ts/metrics/dimension.py
ts/metrics/metric.py
ts/metrics/metric_abstract.py
ts/metrics/metric_cache_abstract.py
ts/metrics/metric_cache_errors.py
ts/metrics/metric_cache_yaml_impl.py
ts/metrics/metric_collector.py
ts/metrics/metric_encoder.py
ts/metrics/metric_type_enum.py
ts/metrics/metrics_store.py
ts/metrics/process_memory_metric.py
ts/metrics/system_metrics.py
ts/metrics/unit.py
ts/model_service/__init__.py
ts/model_service/model_service.py
ts/protocol/__init__.py
ts/protocol/otf_message_handler.py
ts/torch_handler/__init__.py
ts/torch_handler/base_handler.py
ts/torch_handler/contractions.py
ts/torch_handler/dali_handler.py
ts/torch_handler/dali_image_classifier.py
ts/torch_handler/densenet_handler.py
ts/torch_handler/image_classifier.py
ts/torch_handler/image_segmenter.py
ts/torch_handler/object_detector.py
ts/torch_handler/text_classifier.py
ts/torch_handler/text_handler.py
ts/torch_handler/trt_llm_handler.py
ts/torch_handler/vision_handler.py
ts/torch_handler/vllm_handler.py
ts/torch_handler/distributed/__init__.py
ts/torch_handler/distributed/base_deepspeed_handler.py
ts/torch_handler/distributed/base_pippy_handler.py
torchserve_nightly-2025.2.7.dist-info/LICENSE
torchserve_nightly-2025.2.7.dist-info/METADATA
torchserve_nightly-2025.2.7.dist-info/WHEEL
torchserve_nightly-2025.2.7.dist-info/entry_points.txt
torchserve_nightly-2025.2.7.dist-info/top_level.txt
torchserve_nightly-2025.2.7.dist-info/RECORD
