Metadata-Version: 2.2
Name: torchserve-nightly
Version: 2025.2.7
Summary: TorchServe is a tool for serving neural net models for inference
Home-page: https://github.com/pytorch/serve.git
Author: PyTorch Serving team
Author-email: noreply@noreply.com
License: Apache License Version 2.0
Keywords: TorchServe PyTorch Serving Deep Learning Inference AI
License-File: LICENSE
Requires-Dist: Pillow
Requires-Dist: psutil
Requires-Dist: packaging
Requires-Dist: wheel
Provides-Extra: onnx
Requires-Dist: numpy; extra == "onnx"
Requires-Dist: onnx; extra == "onnx"
Requires-Dist: onnx-runtime; extra == "onnx"
Provides-Extra: ipex
Requires-Dist: intel_extension_for_pytorch; extra == "ipex"
Dynamic: author
Dynamic: author-email
Dynamic: description
Dynamic: description-content-type
Dynamic: home-page
Dynamic: keywords
Dynamic: license
Dynamic: provides-extra
Dynamic: requires-dist
Dynamic: summary
